{
	"configurations" : 
	[
		{
			"directories" : 
			[
				{
					"build" : ".",
					"jsonFile" : "directory-.-Debug-f5ebdc15457944623624.json",
					"minimumCMakeVersion" : 
					{
						"string" : "3.28"
					},
					"projectIndex" : 0,
					"source" : ".",
					"targetIndexes" : 
					[
						0,
						1
					]
				}
			],
			"name" : "Debug",
			"projects" : 
			[
				{
					"directoryIndexes" : 
					[
						0
					],
					"name" : "mymalloc",
					"targetIndexes" : 
					[
						0,
						1
					]
				}
			],
			"targets" : 
			[
				{
					"directoryIndex" : 0,
					"id" : "malloc_test::@6890427a1f51a3e7e1df",
					"jsonFile" : "target-malloc_test-Debug-cdb1cc7c437b428ba5ba.json",
					"name" : "malloc_test",
					"projectIndex" : 0
				},
				{
					"directoryIndex" : 0,
					"id" : "mymalloc::@6890427a1f51a3e7e1df",
					"jsonFile" : "target-mymalloc-Debug-49de9d22a9eaa94c6168.json",
					"name" : "mymalloc",
					"projectIndex" : 0
				}
			]
		}
	],
	"kind" : "codemodel",
	"paths" : 
	{
		"build" : "/home/jihu/mymalloc/cmake-build-debug",
		"source" : "/home/jihu/mymalloc"
	},
	"version" : 
	{
		"major" : 2,
		"minor" : 6
	}
}
